{
  "date": "2026-07-16",
  "address": "0x2005d16a84ceefa912d4e380cd32e7ff827875ea",
  "caveats": [
    "⚠️ 誠實聲明：本工具只測「進場價劣化與延遲」，**不測完整損益**（出場價與市場結局未知），",
    "不能由本資料推論跟單能否獲利。本工具不執行任何交易：不下單、不簽章、無私鑰，",
    "只對公開 read-only 端點發 HTTP GET。detect_lag 受輪詢間隔下限影響——真 bot 可用",
    "websocket 更快，故本測值是實際可達延遲的**上界**。不構成投資建議。",
    "⚠️ 時鐘註記：activity 的 timestamp 是鏈上/伺服器時間，本機（runner）時鐘可能有偏移，",
    "detect_lag 可能含 ±數秒的系統時鐘差，數值請當量級參考、不要當精確值。"
  ],
  "sessions": [
    {
      "address": "0x2005d16a84ceefa912d4e380cd32e7ff827875ea",
      "session_stamp": "20260716T001531Z",
      "date": "2026-07-16",
      "started_utc": "2026-07-16T00:15:31+00:00",
      "duration_min": 40.0,
      "poll_sec": 4.0,
      "polls": 573,
      "activity_failures": 0,
      "book_failures": 0,
      "baseline_seeded": 45,
      "jsonl_file": "session_20260716T001531Z.jsonl",
      "stats": {
        "n_detected": 139,
        "n_book_ok": 139,
        "n_book_unavailable": 0,
        "detect_lag_sec": {
          "median": 20.62,
          "p90": 31.85,
          "n": 139
        },
        "adverse_drift": {
          "BUY": {
            "median": 0.058824,
            "p90": 0.190476,
            "n": 139
          },
          "SELL": {
            "median": null,
            "p90": null,
            "n": 0
          }
        },
        "spread": {
          "median": 0.03,
          "n": 139
        },
        "depth_at_best_usd": {
          "median": 502.2,
          "n": 139
        },
        "fixed_copy_usd": 50.0,
        "fillable_at_best_ratio": 0.6115107913669064,
        "fillable_at_best_counts": {
          "fillable": 85,
          "with_depth": 139
        }
      }
    },
    {
      "address": "0x2005d16a84ceefa912d4e380cd32e7ff827875ea",
      "session_stamp": "20260716T023916Z",
      "date": "2026-07-16",
      "started_utc": "2026-07-16T02:39:16+00:00",
      "duration_min": 40.0,
      "poll_sec": 4.0,
      "polls": 581,
      "activity_failures": 0,
      "book_failures": 0,
      "baseline_seeded": 48,
      "jsonl_file": "session_20260716T023916Z.jsonl",
      "stats": {
        "n_detected": 81,
        "n_book_ok": 81,
        "n_book_unavailable": 0,
        "detect_lag_sec": {
          "median": 19.13,
          "p90": 30.83,
          "n": 81
        },
        "adverse_drift": {
          "BUY": {
            "median": 0.045455,
            "p90": 0.222222,
            "n": 81
          },
          "SELL": {
            "median": null,
            "p90": null,
            "n": 0
          }
        },
        "spread": {
          "median": 0.02,
          "n": 80
        },
        "depth_at_best_usd": {
          "median": 197.84,
          "n": 81
        },
        "fixed_copy_usd": 50.0,
        "fillable_at_best_ratio": 0.6296296296296297,
        "fillable_at_best_counts": {
          "fillable": 51,
          "with_depth": 81
        }
      }
    },
    {
      "address": "0x2005d16a84ceefa912d4e380cd32e7ff827875ea",
      "session_stamp": "20260716T160716Z",
      "date": "2026-07-16",
      "started_utc": "2026-07-16T16:07:16+00:00",
      "duration_min": 40.0,
      "poll_sec": 4.0,
      "polls": 553,
      "activity_failures": 0,
      "book_failures": 0,
      "baseline_seeded": 47,
      "jsonl_file": "session_20260716T160716Z.jsonl",
      "stats": {
        "n_detected": 490,
        "n_book_ok": 490,
        "n_book_unavailable": 0,
        "detect_lag_sec": {
          "median": 20.229999999999997,
          "p90": 31.09,
          "n": 490
        },
        "adverse_drift": {
          "BUY": {
            "median": 0.035714,
            "p90": 0.2,
            "n": 490
          },
          "SELL": {
            "median": null,
            "p90": null,
            "n": 0
          }
        },
        "spread": {
          "median": 0.01,
          "n": 489
        },
        "depth_at_best_usd": {
          "median": 242.87,
          "n": 490
        },
        "fixed_copy_usd": 50.0,
        "fillable_at_best_ratio": 0.7061224489795919,
        "fillable_at_best_counts": {
          "fillable": 346,
          "with_depth": 490
        }
      }
    }
  ]
}